{
    "class_name":"八年级1班",
    "class_id":1,
    "total_student":64,
    "actual_student":55,
    "desk_list":[
    	[
    		{
	            "desk_id":1,
	            "student":{
	                "student_id":1,
	                "student_name":"学生1"
	            }
	        },
	        {
	            "desk_id":2,
	            "student":{
	                "student_id":2,
	                "student_name":"学生2"
	            }
	        },
	        {
	            "desk_id":3,
	            "student":{
	                "student_id":3,
	                "student_name":"学生3"
	            }
	        },
	        {
	            "desk_id":4,
	            "student":{
	                "student_id":4,
	                "student_name":"学生4"
	            }
	        },
	        {
	            "desk_id":5,
	            "student":{
	                "student_id":5,
	                "student_name":"学生5"
	            }
	        }
    	],
        [
        	{
            "desk_id":9,
	            "student":{
	                "student_id":9,
	                "student_name":"学生9"
	            }
	        },
	        {
	            "desk_id":10,
	            "student":{
	                "student_id":10,
	                "student_name":"学生10"
	            }
	        },{
	            "desk_id":11,
	            "student":null
	        },
	        {
	            "desk_id":12,
	            "student":{
	                "student_id":12,
	                "student_name":"学生12"
	            }
	        },
	        {
	            "desk_id":13,
	            "student":{
	                "student_id":13,
	                "student_name":"学生13"
	            }
	        }
        ],
        [
        	{
	            "desk_id":17,
	            "student":{
	                "student_id":17,
	                "student_name":"学生17"
	            }
	        },
	        {
	            "desk_id":18,
	            "student":{
	                "student_id":18,
	                "student_name":"学生18"
	            }
	        },
	        {
	            "desk_id":19,
	            "student":{
	                "student_id":19,
	                "student_name":"学生19"
	            }
	        },
	        {
	            "desk_id":20,
	            "student":null
	        },
	        {
	            "desk_id":21,
	            "student":{
	                "student_id":21,
	                "student_name":"学生21"
	            }
	        }
        ],
        [
        	{
	            "desk_id":25,
	            "student":{
	                "student_id":25,
	                "student_name":"学生25"
	            }
	        }
        ]
        
    ]
}